{
  "sections": {
    "main": {
      "type": "main-page",
      "settings": {
      }
    },
    "form": {
      "type": "contact-form",
      "settings": {
        "heading": ""
      }
    },
    "1641224137037b1ea7": {
      "type": "kz-custom-liquid",
      "disabled": true,
      "settings": {
        "title": "",
        "custom_liquid": "<div class=\"klaviyo-form-V4Y7U7\"><\/div>\n<p style=\"text-align: center;\">You are welcome to call us toll-free, 24 hours a day 7 days a week at (855) 440-0375.<\/p>\n<p style=\"text-align: center;\"><em><span style=\"font-size: 12px;\">*By completing this form you are signing up to receive our emails and can unsubscribe at any time. <\/span><\/em><\/p>"
      }
    }
  },
  "order": [
    "main",
    "form",
    "1641224137037b1ea7"
  ]
}
